powerpax/__init__.py
powerpax/_loop.py
powerpax/_tree.py
powerpax/_vmap.py
powerpax-0.2.1.dist-info/licenses/LICENSE.txt
powerpax-0.2.1.dist-info/WHEEL
powerpax-0.2.1.dist-info/METADATA
powerpax-0.2.1.dist-info/RECORD
