Metadata-Version: 2.4
Name: powerpax
Version: 0.2.1
Summary: Small collection of useful utilities for JAX
Author: Karl Otness
Requires-Python: >=3.10
License-Expression: MIT
Classifier: Development Status :: 2 - Pre-Alpha
Classifier: Operating System :: OS Independent
Classifier: Intended Audience :: Science/Research
Classifier: Topic :: Scientific/Engineering
Classifier: Programming Language :: Python
Classifier: Programming Language :: Python :: 3
Classifier: Programming Language :: Python :: 3 :: Only
Classifier: Programming Language :: Python :: 3.10
Classifier: Programming Language :: Python :: 3.11
Classifier: Programming Language :: Python :: 3.12
Classifier: Programming Language :: Python :: 3.13
Classifier: Programming Language :: Python :: 3.14
License-File: LICENSE.txt
Requires-Dist: jax>=0.4.6
Project-URL: Bug Tracker, https://github.com/karlotness/powerpax/issues
Project-URL: Documentation, https://powerpax.readthedocs.io
Project-URL: Homepage, https://github.com/karlotness/powerpax
Project-URL: Source Code, https://github.com/karlotness/powerpax
